MANIFEST.in
setup.cfg
setup.py
question_creator_distributable_bundled_02/User.sqlite3
question_creator_distributable_bundled_02/User.txt
question_creator_distributable_bundled_02/__main__.py
question_creator_distributable_bundled_02/auth.py
question_creator_distributable_bundled_02/data_process.py
question_creator_distributable_bundled_02/load_data.py
question_creator_distributable_bundled_02/requirements.txt
question_creator_distributable_bundled_02.egg-info/PKG-INFO
question_creator_distributable_bundled_02.egg-info/SOURCES.txt
question_creator_distributable_bundled_02.egg-info/dependency_links.txt
question_creator_distributable_bundled_02.egg-info/entry_points.txt
question_creator_distributable_bundled_02.egg-info/requires.txt
question_creator_distributable_bundled_02.egg-info/top_level.txt
question_creator_distributable_bundled_02/cloud_backup/User.sqlite3
question_creator_distributable_bundled_02/react/build/asset-manifest.json
question_creator_distributable_bundled_02/react/build/favicon.ico
question_creator_distributable_bundled_02/react/build/index.html
question_creator_distributable_bundled_02/react/build/logo192.png
question_creator_distributable_bundled_02/react/build/logo512.png
question_creator_distributable_bundled_02/react/build/manifest.json
question_creator_distributable_bundled_02/react/build/robots.txt
question_creator_distributable_bundled_02/react/build/static/css/2.9a2a5986.chunk.css
question_creator_distributable_bundled_02/react/build/static/css/2.9a2a5986.chunk.css.map
question_creator_distributable_bundled_02/react/build/static/css/main.a2906f5f.chunk.css
question_creator_distributable_bundled_02/react/build/static/css/main.a2906f5f.chunk.css.map
question_creator_distributable_bundled_02/react/build/static/js/2.1393a7b9.chunk.js
question_creator_distributable_bundled_02/react/build/static/js/2.1393a7b9.chunk.js.LICENSE.txt
question_creator_distributable_bundled_02/react/build/static/js/2.1393a7b9.chunk.js.map
question_creator_distributable_bundled_02/react/build/static/js/3.94c7fce7.chunk.js
question_creator_distributable_bundled_02/react/build/static/js/3.94c7fce7.chunk.js.map
question_creator_distributable_bundled_02/react/build/static/js/main.c67aef9b.chunk.js
question_creator_distributable_bundled_02/react/build/static/js/main.c67aef9b.chunk.js.map
