Metadata-Version: 1.1
Name: question-creator-distributable-bundled-02
Version: 0.1
Summary: Question creator
Home-page: https://github.com/vishnuprasadkv55/question-creator-distributable-pip
Author: Vishnu Prasad
Author-email: vishnuprasadkv55@gmail.com
License: MIT
Download-URL: https://github.com/vishnuprasadkv55/question-creator-distributable-pip/archive/0.1.tar.gz
Keywords: SOME,MEANINGFULL,KEYWORDS
Platform: UNKNOWN
Classifier: Development Status :: 3 - Alpha
Classifier: Intended Audience :: Developers
Classifier: Topic :: Software Development :: Build Tools
Classifier: License :: OSI Approved :: MIT License
Classifier: Programming Language :: Python :: 3
Classifier: Programming Language :: Python :: 3.4
Classifier: Programming Language :: Python :: 3.5
Classifier: Programming Language :: Python :: 3.6
